{
    "name":"googlemaps",
    "displayName":"Google Maps",
    "packageType": "Web-Component",
    "icon": "https://github.com/Servoy/svyGMaps/raw/master/icon.png",
    "description": "A component for viewing and interacting with Google Maps in Servoy's NG & Titanium Clients.",
    "wikiUrl": "https://github.com/Servoy/svyGMaps/wiki",
    "sourceUrl" : "https://github.com/Servoy/svyGMaps",
    "releases" : [
        {"version":"1.0.0","url":"https://github.com/Servoy/svyGMaps/releases/download/1.0.0/googlemaps.zip"},
        {"version":"1.0.1","url":"https://github.com/Servoy/svyGMaps/releases/download/1.0.1/googlemaps.zip"},
        {"version":"2.0.0","url":"https://github.com/Servoy/svyGMaps/releases/download/2.0.0/googlemaps.zip"},
        {"version":"2.1.0","url":"https://github.com/Servoy/svyGMaps/releases/download/2.1.0/googlemaps.zip"},
        {"version":"2.1.1","url":"https://github.com/Servoy/svyGMaps/releases/download/2.1.1/googlemaps.zip"},
        {"version":"2.2.0","url":"https://github.com/Servoy/svyGMaps/releases/download/2.2.0/googlemaps.zip"},
        {"version":"2.3.0","url":"https://github.com/Servoy/svyGMaps/releases/download/v2.3.0/googlemaps.zip","servoy-version":"2021.3"},
        {"version":"2.3.1","url":"https://github.com/Servoy/svyGMaps/releases/download/v2.3.1/googlemaps.zip","servoy-version":"2021.3"},
        {"version":"2022.3.0","url":"https://github.com/Servoy/svyGMaps/releases/download/v2022.3.0/googlemaps.zip","servoy-version":"2022.3"},
        {"version":"2022.9.0","url":"https://github.com/Servoy/svyGMaps/releases/download/v2022.9.0/googlemaps.zip","servoy-version":"2022.9"},
        {"version":"2024.9.0","url":"https://github.com/Servoy/svyGMaps/releases/download/v2024.9.0/googlemaps.zip","servoy-version":"2024.9"},
        {"version":"2025.3.0","url":"https://github.com/Servoy/svyGMaps/releases/download/v2025.3.0/googlemaps.zip","servoy-version":"2025.3"}

        
    ]
}
